mongo_aggregation/MongoAggregation.py
mongo_aggregation/MongoMatchFilter.py
mongo_aggregation/__init__.py
mongo_aggregation/patterns.py
mongo_aggregation-1.0.1.dist-info/METADATA
mongo_aggregation-1.0.1.dist-info/WHEEL
mongo_aggregation-1.0.1.dist-info/top_level.txt
mongo_aggregation-1.0.1.dist-info/RECORD
