Metadata-Version: 2.1
Name: mongo-aggregation
Version: 1.0.1
Summary: Python MongoDB aggregation ORM
Home-page: https://github.com/egorgvo/mongo_aggregation
Author: Egor Gvo
Author-email: work.egvo@ya.ru
License: MIT
Platform: UNKNOWN
Classifier: License :: OSI Approved :: MIT License
Classifier: Programming Language :: Python :: 3
